{
    "apiLevel": 29,
    "appliedPolicyName": "enterprises/LC02kggfh1/policies/policy1",
    "appliedPolicyVersion": "11",
    "appliedState": "ACTIVE",
    "enrollmentTime": "2021-05-12T02:59:49.610Z",
    "enrollmentTokenName": "enterprises/LC02kggfh1/enrollmentTokens/mbVwF6s8eHV4hd_S7uzQl9AFDUy6SJoZTEo2HnYKIKc",
    "hardwareInfo": {
        "brand": "Laser",
        "hardware": "A50",
        "manufacturer": "incar",
        "model": "MID_1089IPS",
        "serialNumber": "3c0014056441073248e"
    },
    "lastPolicySyncTime": "2021-05-12T05:40:54.252Z",
    "lastStatusReportTime": "2021-05-12T05:14:08.831Z",
    "managementMode": "DEVICE_OWNER",
    "memoryInfo": {
        "totalInternalStorage": "598638592",
        "totalRam": "2093760512"
    },
    "name": "enterprises/LC02kggfh1/devices/35132f656b47c34f",
    "nonComplianceDetails": [
        {
            "installationFailureReason": "INSTALLATION_FAILURE_REASON_UNKNOWN",
            "nonComplianceReason": "APP_NOT_INSTALLED",
            "packageName": "com.real.launcher.wp.ten",
            "settingName": "applications"
        },
        {
            "installationFailureReason": "NOT_FOUND",
            "nonComplianceReason": "APP_NOT_INSTALLED",
            "packageName": "com.anpmech.launcher",
            "settingName": "applications"
        },
        {
            "installationFailureReason": "NOT_FOUND",
            "nonComplianceReason": "APP_NOT_INSTALLED",
            "packageName": "com.easwareapps.g2l",
            "settingName": "applications"
        },
        {
            "installationFailureReason": "NOT_FOUND",
            "nonComplianceReason": "APP_NOT_INSTALLED",
            "packageName": "com.gacode.relaunchx",
            "settingName": "applications"
        },
        {
            "installationFailureReason": "INSTALLATION_FAILURE_REASON_UNKNOWN",
            "nonComplianceReason": "APP_NOT_INSTALLED",
            "packageName": "com.github.postapczuk.lalauncher",
            "settingName": "applications"
        },
        {
            "installationFailureReason": "NOT_FOUND",
            "nonComplianceReason": "APP_NOT_INSTALLED",
            "packageName": "com.github.rsteube.t4",
            "settingName": "applications"
        },
        {
            "installationFailureReason": "NOT_FOUND",
            "nonComplianceReason": "APP_NOT_INSTALLED",
            "packageName": "com.harasoft.relaunch",
            "settingName": "applications"
        },
        {
            "installationFailureReason": "NOT_FOUND",
            "nonComplianceReason": "APP_NOT_INSTALLED",
            "packageName": "com.jkuester.unlauncher",
            "settingName": "applications"
        },
        {
            "installationFailureReason": "NOT_FOUND",
            "nonComplianceReason": "APP_NOT_INSTALLED",
            "packageName": "com.kaneoriley.cyanogenport.launcher3",
            "settingName": "applications"
        },
        {
            "installationFailureReason": "NOT_FOUND",
            "nonComplianceReason": "APP_NOT_INSTALLED",
            "packageName": "com.launcher.silverfish",
            "settingName": "applications"
        },
        {
            "installationFailureReason": "NOT_COMPATIBLE_WITH_DEVICE",
            "nonComplianceReason": "APP_NOT_INSTALLED",
            "packageName": "com.mirasmithy.epochlauncher",
            "settingName": "applications"
        },
        {
            "installationFailureReason": "INSTALLATION_FAILURE_REASON_UNKNOWN",
            "nonComplianceReason": "APP_NOT_INSTALLED",
            "packageName": "com.notriddle.null_launcer",
            "settingName": "applications"
        },
        {
            "installationFailureReason": "NOT_FOUND",
            "nonComplianceReason": "APP_NOT_INSTALLED",
            "packageName": "com.quaap.launchtime",
            "settingName": "applications"
        },
        {
            "installationFailureReason": "INSTALLATION_FAILURE_REASON_UNKNOWN",
            "nonComplianceReason": "APP_NOT_INSTALLED",
            "packageName": "com.sduduzog.slimlauncher",
            "settingName": "applications"
        },
        {
            "installationFailureReason": "NOT_APPROVED",
            "nonComplianceReason": "APP_NOT_INSTALLED",
            "packageName": "com.smithdtyler.prettygoodmusicplayer.launchermode",
            "settingName": "applications"
        },
        {
            "installationFailureReason": "NOT_FOUND",
            "nonComplianceReason": "APP_NOT_INSTALLED",
            "packageName": "com.szchoiceway.aios.bridge",
            "settingName": "applications"
        },
        {
            "installationFailureReason": "INSTALLATION_FAILURE_REASON_UNKNOWN",
            "nonComplianceReason": "APP_NOT_INSTALLED",
            "packageName": "com.twsitedapps.homemanager",
            "settingName": "applications"
        },
        {
            "installationFailureReason": "INSTALLATION_FAILURE_REASON_UNKNOWN",
            "nonComplianceReason": "APP_NOT_INSTALLED",
            "packageName": "com.vackosar.searchbasedlauncher",
            "settingName": "applications"
        },
        {
            "installationFailureReason": "NOT_FOUND",
            "nonComplianceReason": "APP_NOT_INSTALLED",
            "packageName": "com.vincent_falzon.discreetlauncher",
            "settingName": "applications"
        },
        {
            "installationFailureReason": "NOT_FOUND",
            "nonComplianceReason": "APP_NOT_INSTALLED",
            "packageName": "community.fairphone.fplauncher3",
            "settingName": "applications"
        },
        {
            "installationFailureReason": "NOT_FOUND",
            "nonComplianceReason": "APP_NOT_INSTALLED",
            "packageName": "community.fairphone.launcher",
            "settingName": "applications"
        },
        {
            "installationFailureReason": "NOT_FOUND",
            "nonComplianceReason": "APP_NOT_INSTALLED",
            "packageName": "de.clemensbartz.android.launcher",
            "settingName": "applications"
        },
        {
            "installationFailureReason": "INSTALLATION_FAILURE_REASON_UNKNOWN",
            "nonComplianceReason": "APP_NOT_INSTALLED",
            "packageName": "de.devmil.paperlaunch",
            "settingName": "applications"
        },
        {
            "installationFailureReason": "INSTALLATION_FAILURE_REASON_UNKNOWN",
            "nonComplianceReason": "APP_NOT_INSTALLED",
            "packageName": "de.markusfisch.android.pielauncher",
            "settingName": "applications"
        },
        {
            "installationFailureReason": "NOT_FOUND",
            "nonComplianceReason": "APP_NOT_INSTALLED",
            "packageName": "de.nodomain.tobihille.seniorlauncher",
            "settingName": "applications"
        },
        {
            "installationFailureReason": "INSTALLATION_FAILURE_REASON_UNKNOWN",
            "nonComplianceReason": "APP_NOT_INSTALLED",
            "packageName": "de.szalkowski.activitylauncher",
            "settingName": "applications"
        },
        {
            "installationFailureReason": "NOT_FOUND",
            "nonComplianceReason": "APP_NOT_INSTALLED",
            "packageName": "foundation.e.blisslauncher",
            "settingName": "applications"
        },
        {
            "installationFailureReason": "INSTALLATION_FAILURE_REASON_UNKNOWN",
            "nonComplianceReason": "APP_NOT_INSTALLED",
            "packageName": "fr.neamar.kiss",
            "settingName": "applications"
        },
        {
            "installationFailureReason": "NOT_FOUND",
            "nonComplianceReason": "APP_NOT_INSTALLED",
            "packageName": "io.github.subhamtyagi.lastlauncher",
            "settingName": "applications"
        },
        {
            "installationFailureReason": "NOT_FOUND",
            "nonComplianceReason": "APP_NOT_INSTALLED",
            "packageName": "kr.hybdms.sidepanel",
            "settingName": "applications"
        },
        {
            "installationFailureReason": "NOT_FOUND",
            "nonComplianceReason": "APP_NOT_INSTALLED",
            "packageName": "luke.launcher",
            "settingName": "applications"
        },
        {
            "installationFailureReason": "INSTALLATION_FAILURE_REASON_UNKNOWN",
            "nonComplianceReason": "APP_NOT_INSTALLED",
            "packageName": "mono.hg",
            "settingName": "applications"
        },
        {
            "installationFailureReason": "INSTALLATION_FAILURE_REASON_UNKNOWN",
            "nonComplianceReason": "APP_NOT_INSTALLED",
            "packageName": "net.nhiroki.bluelineconsole",
            "settingName": "applications"
        },
        {
            "installationFailureReason": "NOT_APPROVED",
            "nonComplianceReason": "APP_NOT_INSTALLED",
            "packageName": "ohi.andre.consolelauncher",
            "settingName": "applications"
        },
        {
            "installationFailureReason": "NOT_FOUND",
            "nonComplianceReason": "APP_NOT_INSTALLED",
            "packageName": "org.xphnx.ameixa",
            "settingName": "applications"
        },
        {
            "installationFailureReason": "NOT_FOUND",
            "nonComplianceReason": "APP_NOT_INSTALLED",
            "packageName": "org.zimmob.zimlx",
            "settingName": "applications"
        },
        {
            "installationFailureReason": "INSTALLATION_FAILURE_REASON_UNKNOWN",
            "nonComplianceReason": "APP_NOT_INSTALLED",
            "packageName": "posidon.launcher",
            "settingName": "applications"
        },
        {
            "installationFailureReason": "NOT_FOUND",
            "nonComplianceReason": "APP_NOT_INSTALLED",
            "packageName": "rocks.tbog.tblauncher",
            "settingName": "applications"
        },
        {
            "installationFailureReason": "NOT_COMPATIBLE_WITH_DEVICE",
            "nonComplianceReason": "APP_NOT_INSTALLED",
            "packageName": "com.google.android.GoogleCamera",
            "settingName": "applications"
        },
        {
            "installationFailureReason": "NOT_COMPATIBLE_WITH_DEVICE",
            "nonComplianceReason": "APP_NOT_INSTALLED",
            "packageName": "com.google.android.apps.podcasts",
            "settingName": "applications"
        },
        {
            "installationFailureReason": "NOT_COMPATIBLE_WITH_DEVICE",
            "nonComplianceReason": "APP_NOT_INSTALLED",
            "packageName": "com.google.android.apps.messaging",
            "settingName": "applications"
        },
        {
            "installationFailureReason": "NOT_COMPATIBLE_WITH_DEVICE",
            "nonComplianceReason": "APP_NOT_INSTALLED",
            "packageName": "com.google.android.apps.photos.scanner",
            "settingName": "applications"
        },
        {
            "installationFailureReason": "NOT_COMPATIBLE_WITH_DEVICE",
            "nonComplianceReason": "APP_NOT_INSTALLED",
            "packageName": "com.google.android.dialer",
            "settingName": "applications"
        },
        {
            "installationFailureReason": "INSTALLATION_FAILURE_REASON_UNKNOWN",
            "nonComplianceReason": "APP_NOT_INSTALLED",
            "packageName": "com.google.android.googlequicksearchbox",
            "settingName": "applications"
        },
        {
            "installationFailureReason": "NOT_COMPATIBLE_WITH_DEVICE",
            "nonComplianceReason": "APP_NOT_INSTALLED",
            "packageName": "com.google.android.youtube.tvkids",
            "settingName": "applications"
        },
        {
            "installationFailureReason": "NOT_COMPATIBLE_WITH_DEVICE",
            "nonComplianceReason": "APP_NOT_INSTALLED",
            "packageName": "com.google.ar.lens",
            "settingName": "applications"
        },
        {
            "installationFailureReason": "NOT_COMPATIBLE_WITH_DEVICE",
            "nonComplianceReason": "APP_NOT_INSTALLED",
            "packageName": "com.google.tango.measure",
            "settingName": "applications"
        }
    ],
    "ownership": "COMPANY_OWNED",
    "policyCompliant": true,
    "policyName": "enterprises/LC02kggfh1/policies/policy1",
    "previousDeviceNames": [
        "enterprises/LC02kggfh1/devices/3b2767b18f9c4405",
        "enterprises/LC02kggfh1/devices/37977ffdbc26f9db",
        "enterprises/LC02kggfh1/devices/3cebbde468415aad",
        "enterprises/LC02kggfh1/devices/37b0aa3d5905b0ad",
        "enterprises/LC02kggfh1/devices/3715f85817a474fd",
        "enterprises/LC02kggfh1/devices/3f79c67b5fb46dce"
    ],
    "securityPosture": {
        "devicePosture": "SECURE"
    },
    "softwareInfo": {
        "androidBuildNumber": "MID_1089IPS_V01_20200626",
        "androidBuildTime": "2020-06-26T03:37:31Z",
        "androidDevicePolicyVersionCode": 1498020,
        "androidDevicePolicyVersionName": "14.98.02.v39",
        "androidVersion": "10",
        "bootloaderVersion": "unknown",
        "deviceBuildSignature": "7f5088d73143bfcadb55f55bcf77d98d8caa9b68dee882919e5497a7f5fb79d3",
        "deviceKernelVersion": "4.9.170",
        "primaryLanguageCode": "en-AU",
        "securityPatchLevel": "2020-04-05",
        "systemUpdateInfo": {
            "updateStatus": "UP_TO_DATE"
        }
    },
    "state": "ACTIVE",
    "userName": "enterprises/LC02kggfh1/users/109908569614233758988"
}